markdown_include/__init__.py
markdown_include/__main__.py
markdown_include/markdown_include.py
md_incl-0.0.4.dist-info/LICENSE
md_incl-0.0.4.dist-info/METADATA
md_incl-0.0.4.dist-info/WHEEL
md_incl-0.0.4.dist-info/entry_points.txt
md_incl-0.0.4.dist-info/top_level.txt
md_incl-0.0.4.dist-info/RECORD
