Metadata-Version: 2.1
Name: md_incl
Version: 0.0.4
Summary: processes a Markdown file by including the contents of other Markdown files
Author-email: Sean Han <xiaotian.han91@gmail.com>
Project-URL: Homepage, https://github.com/hxtmike/markdown_include
Project-URL: Issues, https://github.com/hxtmike/markdown_include/issues
Classifier: Programming Language :: Python :: 3
Classifier: License :: OSI Approved :: MIT License
Requires-Python: >=3.8
License-File: LICENSE
